facturxlib/__init__.py
facturxlib/basic.py
facturxlib/facturx.py
facturxlib-1.0.dist-info/licenses/LICENSE
facturxlib-1.0.dist-info/METADATA
facturxlib-1.0.dist-info/WHEEL
facturxlib-1.0.dist-info/top_level.txt
facturxlib-1.0.dist-info/RECORD
