Metadata-Version: 2.4
Name: facturxlib
Version: 1.0
Summary: Library to create Factur-X conform CrossIndustryInvoice xml-files.
Home-page: https://github.com/kbr/facturxlib
Author: Klaus Bremer
Author-email: bremer@bremer-media.com
License: MIT
Project-URL: Homepage, https://github.com/kbr/facturxlib
Project-URL: Code, https://github.com/kbr/facturxlib
Project-URL: Issue tracker, https://github.com/kbr/facturxlib/issues
Keywords: Factur-X,ZUGFeRD,CrossIndustryInvoice,xml,E-Invoice,E-Rechnung,X-Rechnung
Platform: any
Classifier: Development Status :: 4 - Beta
Classifier: Intended Audience :: Developers
Classifier: License :: OSI Approved :: MIT License
Classifier: Operating System :: OS Independent
Classifier: Programming Language :: Python
Classifier: Programming Language :: Python :: 3
Classifier: Topic :: Software Development :: Libraries :: Python Modules
Classifier: Topic :: Utilities
License-File: LICENSE
Dynamic: license-file
